japan_holiday
