Metadata-Version: 1.1
Name: japan-holiday
Version: 0.1.0
Summary: Holiday in Japan from Google Calendar.
Home-page: https://github.com/subc/japan_holiday
Author: haminiku
Author-email: haminiku1129@gmail.com
License: MIT License
Keywords: holiday,japan_holiday
Platform: UNKNOWN
Classifier: License :: OSI Approved :: MIT License
Classifier: Programming Language :: Python
Classifier: Programming Language :: Python :: 2.6
Classifier: Programming Language :: Python :: 2.7
Classifier: Programming Language :: Python :: 3
Classifier: Programming Language :: Python :: 3.3
Classifier: Programming Language :: Python :: 3.4
